numpy_adjoint/__init__.py
numpy_adjoint/array.py
pyadjoint/__init__.py
pyadjoint/adjfloat.py
pyadjoint/block.py
pyadjoint/block_variable.py
pyadjoint/checkpointing.py
pyadjoint/control.py
pyadjoint/drivers.py
pyadjoint/enlisting.py
pyadjoint/ipopt.py
pyadjoint/ordered_set.py
pyadjoint/overloaded_function.py
pyadjoint/overloaded_type.py
pyadjoint/placeholder.py
pyadjoint/reduced_functional.py
pyadjoint/reduced_functional_numpy.py
pyadjoint/tape.py
pyadjoint/verification.py
pyadjoint/optimization/__init__.py
pyadjoint/optimization/constraints.py
pyadjoint/optimization/ipopt_solver.py
pyadjoint/optimization/moola_problem.py
pyadjoint/optimization/optimization.py
pyadjoint/optimization/optimization_problem.py
pyadjoint/optimization/optimization_solver.py
pyadjoint/optimization/rol_solver.py
pyadjoint/optimization/tao_solver.py
pyadjoint_ad-2025.10.1.dist-info/licenses/LICENSE
pyadjoint_ad-2025.10.1.dist-info/METADATA
pyadjoint_ad-2025.10.1.dist-info/WHEEL
pyadjoint_ad-2025.10.1.dist-info/top_level.txt
pyadjoint_ad-2025.10.1.dist-info/RECORD
