Metadata-Version: 2.4
Name: pyadjoint-ad
Version: 2025.10.1
Summary: High-level automatic differentiation library
Author-email: "Jørgen S. Dokken" <dokken@simula.no>
License:                    GNU LESSER GENERAL PUBLIC LICENSE
Project-URL: Repository, https://github.com/dolfin-adjoint/pyadjoint.git
Classifier: Programming Language :: Python
License-File: LICENSE
Requires-Dist: checkpoint_schedules
Requires-Dist: scipy>=1.0
Requires-Dist: sympy
Provides-Extra: all
Requires-Dist: coverage; extra == "all"
Requires-Dist: flake8; extra == "all"
Requires-Dist: meshio; extra == "all"
Requires-Dist: moola>=0.1.6; extra == "all"
Requires-Dist: networkx; extra == "all"
Requires-Dist: protobuf; extra == "all"
Requires-Dist: pygmsh; extra == "all"
Requires-Dist: pygraphviz; extra == "all"
Requires-Dist: pytest>=3.10; extra == "all"
Requires-Dist: sphinx; extra == "all"
Requires-Dist: sphinx-autobuild; extra == "all"
Requires-Dist: sphinxcontrib-bibtex; extra == "all"
Requires-Dist: tensorflow; extra == "all"
Provides-Extra: doc
Requires-Dist: sphinx; extra == "doc"
Requires-Dist: sphinx-autobuild; extra == "doc"
Requires-Dist: sphinxcontrib-bibtex; extra == "doc"
Provides-Extra: meshing
Requires-Dist: pygmsh; extra == "meshing"
Requires-Dist: meshio; extra == "meshing"
Provides-Extra: moola
Requires-Dist: moola>=0.1.6; extra == "moola"
Provides-Extra: test
Requires-Dist: pytest>=3.10; extra == "test"
Requires-Dist: flake8; extra == "test"
Requires-Dist: coverage; extra == "test"
Provides-Extra: visualisation
Requires-Dist: tensorflow; extra == "visualisation"
Requires-Dist: protobuf; extra == "visualisation"
Requires-Dist: networkx; extra == "visualisation"
Requires-Dist: pygraphviz; extra == "visualisation"
Provides-Extra: tao
Requires-Dist: petsc4py; extra == "tao"
Requires-Dist: petsctools>2025.0; extra == "tao"
Dynamic: license-file
